repeated_adder/repeated_adder.v
module repeated_adder (
    input clk,         
    input reset, 
    input start,  
    input [3:0] A,  
    input [3:0] B,    
    output reg [7:0] product, 
    output reg done   
);

    localparam IDLE = 1'b0; 
    localparam MULTIPLY = 1'b1;

    reg state;          // Current state
    reg [3:0] A_reg;   // Multiplicand register
    reg [3:0] B_reg;   // Multiplier register
    reg [7:0] prod_reg; // Product register

    always @(posedge clk or posedge reset) begin
        if (reset) begin
            // Reset all registers
            state <= IDLE;
            A_reg <= 4'b0;
            B_reg <= 4'b0;
            prod_reg <= 8'b0;
            done <= 1'b0;
        end else begin
            case (state)
                IDLE: begin
                    done <= 1'b0;
                    if (start) begin
                        A_reg <= A;
                        B_reg <= B;
                        prod_reg <= 8'b0;
                        state <= MULTIPLY;
                    end
                end
                
                MULTIPLY: begin
                    if (B_reg != 0) begin
                        prod_reg <= prod_reg + A_reg;
                        B_reg <= B_reg - 1;
                    end else begin
                        done <= 1'b1;
                        state <= IDLE;
                    end
                end
            endcase
        end
    end

    always @(*) begin
        product = prod_reg;
    end

endmodule

repeated_adder/repeated_adder_tb.v
`timescale 1ns/1ps
`include "repeated_adder.v"


module repeated_adder_tb;
    // Test bench signals
    reg clk;
    reg reset;
    reg start;
    reg [3:0] A;
    reg [3:0] B;
    wire [7:0] product;
    wire done;

    // Instantiate the repeated_adder
    repeated_adder uut (
        .clk(clk),
        .reset(reset),
        .start(start),
        .A(A),
        .B(B),
        .product(product),
        .done(done)
    );

    // Clock generation
    always begin
        #5 clk = ~clk;
    end

    // Test stimulus
    initial begin
        // Initialize signals
        clk = 0;
        reset = 1;
        start = 0;
        A = 0;
        B = 0;

        // Release reset
        #20;
        reset = 0;
        #10;

        // Test case 1: 3 x 4 = 12
        A = 4'h3;
        B = 4'h4;
        start = 1;
        #10;
        start = 0;
        wait(done);
        if (product === 8'h0C)
            $display("Test case 1 passed: 3 x 4 = %d", product);
        else
            $display("Test case 1 failed: Expected 12, got %d", product);
        #20;

        // Test case 2: 7 x 5 = 35
        A = 4'h7;
        B = 4'h5;
        start = 1;
        #10;
        start = 0;
        wait(done);
        if (product === 8'h23)
            $display("Test case 2 passed: 7 x 5 = %d", product);
        else
            $display("Test case 2 failed: Expected 35, got %d", product);
        #20;

        // Test case 3: 15 x 15 = 225
        A = 4'hF;
        B = 4'hF;
        start = 1;
        #10;
        start = 0;
        wait(done);
        if (product === 8'hE1)
            $display("Test case 3 passed: 15 x 15 = %d", product);
        else
            $display("Test case 3 failed: Expected 225, got %d", product);

        // Add some delay and finish simulation
        #100;
        $display("Simulation completed");
        $finish;
    end

    // Optional: Generate VCD file for waveform viewing
    initial begin
        $dumpfile("repeated_adder_tb.vcd");
        $dumpvars(0, repeated_adder_tb);
    end

endmodule

repeated_adder/repeated_adder_tb.vcd
$date
	Tue Feb 11 11:13:19 2025
$end
$version
	Icarus Verilog
$end
$timescale
	1ps
$end
$scope module repeated_adder_tb $end
$var wire 8 ! product [7:0] $end
$var wire 1 " done $end
$var reg 4 # A [3:0] $end
$var reg 4 $ B [3:0] $end
$var reg 1 % clk $end
$var reg 1 & reset $end
$var reg 1 ' start $end
$scope module uut $end
$var wire 4 ( A [3:0] $end
$var wire 4 ) B [3:0] $end
$var wire 1 % clk $end
$var wire 1 & reset $end
$var wire 1 ' start $end
$var reg 4 * A_reg [3:0] $end
$var reg 4 + B_reg [3:0] $end
$var reg 1 " done $end
$var reg 8 , prod_reg [7:0] $end
$var reg 8 - product [7:0] $end
$var reg 1 . state $end
$upscope $end
$upscope $end
$enddefinitions $end
#0
$dumpvars
0.
b0 -
b0 ,
b0 +
b0 *
b0 )
b0 (
0'
1&
0%
b0 $
b0 #
0"
b0 !
$end
#5000
1%
#10000
0%
#15000
1%
#20000
0%
0&
#25000
1%
#30000
0%
1'
b100 $
b100 )
b11 #
b11 (
#35000
1.
b100 +
b11 *
1%
#40000
0%
0'
#45000
b11 !
b11 -
b11 +
b11 ,
1%
#50000
0%
#55000
b110 !
b110 -
b10 +
b110 ,
1%
#60000
0%
#65000
b1001 !
b1001 -
b1 +
b1001 ,
1%
#70000
0%
#75000
b1100 !
b1100 -
b0 +
b1100 ,
1%
#80000
0%
#85000
0.
1"
1%
#90000
0%
#95000
0"
1%
#100000
0%
#105000
b0 !
b0 -
1.
b0 ,
b101 +
b111 *
1%
1'
b101 $
b101 )
b111 #
b111 (
#110000
0%
#115000
b111 !
b111 -
b100 +
b111 ,
1%
0'
#120000
0%
#125000
b1110 !
b1110 -
b11 +
b1110 ,
1%
#130000
0%
#135000
b10101 !
b10101 -
b10 +
b10101 ,
1%
#140000
0%
#145000
b11100 !
b11100 -
b1 +
b11100 ,
1%
#150000
0%
#155000
b100011 !
b100011 -
b0 +
b100011 ,
1%
#160000
0%
#165000
0.
1"
1%
#170000
0%
#175000
0"
1%
#180000
0%
#185000
b0 !
b0 -
1.
b0 ,
b1111 +
b1111 *
1%
1'
b1111 $
b1111 )
b1111 #
b1111 (
#190000
0%
#195000
b1111 !
b1111 -
b1110 +
b1111 ,
1%
0'
#200000
0%
#205000
b11110 !
b11110 -
b1101 +
b11110 ,
1%
#210000
0%
#215000
b101101 !
b101101 -
b1100 +
b101101 ,
1%
#220000
0%
#225000
b111100 !
b111100 -
b1011 +
b111100 ,
1%
#230000
0%
#235000
b1001011 !
b1001011 -
b1010 +
b1001011 ,
1%
#240000
0%
#245000
b1011010 !
b1011010 -
b1001 +
b1011010 ,
1%
#250000
0%
#255000
b1101001 !
b1101001 -
b1000 +
b1101001 ,
1%
#260000
0%
#265000
b1111000 !
b1111000 -
b111 +
b1111000 ,
1%
#270000
0%
#275000
b10000111 !
b10000111 -
b110 +
b10000111 ,
1%
#280000
0%
#285000
b10010110 !
b10010110 -
b101 +
b10010110 ,
1%
#290000
0%
#295000
b10100101 !
b10100101 -
b100 +
b10100101 ,
1%
#300000
0%
#305000
b10110100 !
b10110100 -
b11 +
b10110100 ,
1%
#310000
0%
#315000
b11000011 !
b11000011 -
b10 +
b11000011 ,
1%
#320000
0%
#325000
b11010010 !
b11010010 -
b1 +
b11010010 ,
1%
#330000
0%
#335000
b11100001 !
b11100001 -
b0 +
b11100001 ,
1%
#340000
0%
#345000
0.
1"
1%
#350000
0%
#355000
0"
1%
