pipelines/pipelineProcessor.v
module pipe (
    output [15:0] zout,
    input [3:0] rs1, rs2, rd,
    input clk1, clk2,
    input [3:0] func,
    input [7:0] addr
);
    reg [15:0] l1a, l1b, l2z, l3z;
    reg [7:0] l1add, l2add, l3add;
    reg [3:0] l1func, l1rd, l2rd;
    reg [15:0] regbank [0:15];
    reg [15:0] membank [0:255];

    assign zout = l3z;

    // Stage 1: Fetch/Decode (clk1)
    always @(posedge clk1) begin
        l1a <= regbank[rs1];
        l1b <= regbank[rs2];
        l1func <= func;
        l1rd <= rd;
        l1add <= addr;
    end

    // Stage 2: Execute (clk2)
    always @(posedge clk2) begin
        case (l1func)
            0: l2z <= l1a + l1b;
            1: l2z <= l1a - l1b;
            2: l2z <= l1a * l1b;
            3: l2z <= l1a;
            4: l2z <= l1b;
            5: l2z <= l1a & l1b;
            6: l2z <= l1a | l1b;
            7: l2z <= l1a ^ l1b;
            8: l2z <= ~l1a;
            9: l2z <= ~l1b;
            10: l2z <= l1a >> 1;
            11: l2z <= l1b << 1;
            default: l2z <= 0;
        endcase
        l2rd <= l1rd;
        l2add <= l1add;
    end

    // Stage 3: Destination Register/Write Back to Register (clk1)
    always @(posedge clk1) begin
        regbank[l2rd] <= l2z;
        l3z <= l2z;
        l3add <= l2add;
    end

    // Stage 4: Write Back to Memory (clk2)
    always @(posedge clk2) begin
        membank[l3add] <= l3z;
    end
endmodule

pipelines/pipelineProcessor_tb.v
module simuli;
    reg [3:0] rs1, rs2, rd, func;
    reg [7:0] addr;
    wire [15:0] zout;
    reg clk1, clk2;
    integer k, i;

    pipe pipe_inst (zout, rs1, rs2, rd, func, addr, clk1, clk2);

    // Clock generation (non-overlapping)
    initial begin
        clk1 = 0;
        forever #10 clk1 = ~clk1;
    end
    initial begin
        clk2 = 0;
        forever #10 clk2 = ~clk2;
    end

    // VCD dump
    initial begin
        $dumpfile("pipe.vcd");
        $dumpvars(0, simuli);
    end

    // Initialize register file
    initial begin
        #5;
        for (k = 0; k < 15; k = k + 1) begin
            pipe_inst.regbank[k] = k;
        end
    end

    // Test sequence
    initial begin
        // Initialize inputs
        rs1 = 0; rs2 = 0; rd = 0; func = 0; addr = 0;

        // Reset-like delay
        #20;

        // Test 1: Multiply (6 * 1 = 6 -> reg[10], mem[125])
        rs1 = 6; rs2 = 1; rd = 10; addr = 125; func = 2;
        #40 $display("Test 1: reg[10]=%d (expected 6), mem[125]=%d, zout=%d", pipe_inst.regbank[10], pipe_inst.membank[125], zout);

        // Test 2: Move A (reg[9] = 9 -> reg[12], mem[126])
        rs1 = 9; rs2 = 8; rd = 12; addr = 126; func = 3;
        #40 $display("Test 2: reg[12]=%d (expected 9), mem[126]=%d, zout=%d", pipe_inst.regbank[12], pipe_inst.membank[126], zout);

        // Test 3: Move B (reg[4] = 4 -> reg[13], mem[125])
        rs1 = 2; rs2 = 4; rd = 13; addr = 125; func = 4;
        #40 $display("Test 3: reg[13]=%d (expected 4), mem[125]=%d, zout=%d", pipe_inst.regbank[13], pipe_inst.membank[125], zout);

        #20 $finish;
    end
endmodule

pipelines/pipe.vcd
$date
	Tue Apr 22 03:10:03 2025
$end
$version
	Icarus Verilog
$end
$timescale
	1s
$end
$scope module simuli $end
$var wire 16 ! zout [15:0] $end
$var reg 8 " addr [7:0] $end
$var reg 1 # clk1 $end
$var reg 1 $ clk2 $end
$var reg 4 % func [3:0] $end
$var reg 4 & rd [3:0] $end
$var reg 4 ' rs1 [3:0] $end
$var reg 4 ( rs2 [3:0] $end
$var integer 32 ) k [31:0] $end
$scope module pipe_inst $end
$var wire 8 * addr [7:0] $end
$var wire 1 + clk1 $end
$var wire 1 , clk2 $end
$var wire 4 - func [3:0] $end
$var wire 4 . rd [3:0] $end
$var wire 4 / rs1 [3:0] $end
$var wire 4 0 rs2 [3:0] $end
$var wire 16 1 zout [15:0] $end
$var reg 16 2 l1a [15:0] $end
$var reg 8 3 l1add [7:0] $end
$var reg 16 4 l1b [15:0] $end
$var reg 4 5 l1func [3:0] $end
$var reg 4 6 l1rd [3:0] $end
$var reg 8 7 l2add [7:0] $end
$var reg 4 8 l2rd [3:0] $end
$var reg 16 9 l2z [15:0] $end
$var reg 8 : l3add [7:0] $end
$var reg 16 ; l3z [15:0] $end
$upscope $end
$upscope $end
$enddefinitions $end
#0
$dumpvars
bx ;
bx :
bx 9
bx 8
bx 7
bx 6
bx 5
bx 4
bx 3
bx 2
bx 1
b0 0
b0 /
b0 .
b0 -
0,
0+
b0 *
bx )
b0 (
b0 '
b0 &
b0 %
0$
0#
b0 "
bx !
$end
#5
b1111 )
#10
b1 *
1$
b1 -
1#
#20
b0 9
1,
b0 *
0$
b0 -
0#
b10 %
b1111101 "
b1010 &
b1010 .
b1 (
b1 0
b110 '
b110 /
#30
b1 *
1$
b1 -
1#
#40
b0 *
0$
b0 -
0#
#50
b1 *
1$
b1 -
1#
#60
b0 3
b1100 6
b0 5
b1000 4
b1001 2
b0 !
b0 1
b0 ;
1+
0,
b0 *
0$
b0 -
0#
b11 %
b1111110 "
b1100 &
b1100 .
b1000 (
b1000 0
b1001 '
b1001 /
#70
b1 *
1$
b1 -
1#
#80
b0 *
0$
b0 -
0#
#90
b1 *
1$
b1 -
1#
#100
b0 7
b1100 8
b10001 9
0+
1,
b0 *
0$
b0 -
0#
b100 %
b1111101 "
b1101 &
b1101 .
b100 (
b100 0
b10 '
b10 /
#110
b1 *
1$
b1 -
1#
#120
b0 *
0$
b0 -
0#
#130
b1 *
1$
b1 -
1#
#140
b0 *
0$
b0 -
0#
#150
b1 *
1$
b1 -
1#
#160
b0 *
0$
b0 -
0#
