pipelines/pipeline.v
module pipeline (F, A, B, C, D, clk);
    parameter N = 10;

    input [N-1:0] A, B, C, D;
    input clk;
    output [N-1:0] F;
    reg [N-1:0] L12_x1, L12_x2, L12_D, L23_x3, L23_D, L34_F, L34_D;

    assign F = L34_F; 

    always @(posedge clk)
    begin
        // ** STAGE 1 **
        L12_x1 <= #4 A + B;
        L12_x2 <= #4 C - D;
        L12_D  <= D;

        // ** STAGE 2 **
        L23_x3 <= #4 L12_x1 + L12_x2;
        L23_D  <= L12_D;

        // ** STAGE 3 **
        L34_F  <= #6 L23_x3 * L23_D;

        // ** STAGE 4 **
        L34_D  <= L23_D;
        
    end
endmodule

pipelines/pipeline_tb.v
`timescale 1ns/1ps
`include "pipeline.v"

module stimuli;
    parameter N = 10;
    
    reg [N-1:0] A, B, C, D;
    reg clk;
    wire [N-1:0] F;
    
    // Instantiate the pipeline module
    pipeline uut (
        .F(F), 
        .A(A), 
        .B(B), 
        .C(C), 
        .D(D), 
        .clk(clk)
    );

    
    initial begin
        $dumpfile("waveform.vcd");  
        $dumpvars(0, stimuli);      // Dump all variables
        $dumpvars(1, uut);          // Dump internal pipeline registers
    end

    
    // Clock generation
    always #5 clk = ~clk;
    
    initial begin
    clk = 0;  
    A = 10; B = 5; C = 8; D = 3; 
    
    #10;
    A = 15; B = 7; C = 12; D = 4;
    
    #10;
    A = 20; B = 10; C = 14; D = 6;
    
    #10;
    A = 25; B = 12; C = 18; D = 8;
    
    #10; 
    $finish;
end

    
    initial begin
        $monitor("Time=%0t A=%d B=%d C=%d D=%d | F=%d", $time, A, B, C, D, F);
    end
endmodule

pipelines/waveform.vcd
$date
	Tue Mar 25 11:13:30 2025
$end
$version
	Icarus Verilog
$end
$timescale
	1ps
$end
$scope module stimuli $end
$var wire 10 ! F [9:0] $end
$var reg 10 " A [9:0] $end
$var reg 10 # B [9:0] $end
$var reg 10 $ C [9:0] $end
$var reg 10 % D [9:0] $end
$var reg 1 & clk $end
$scope module uut $end
$var wire 10 ' A [9:0] $end
$var wire 10 ( B [9:0] $end
$var wire 10 ) C [9:0] $end
$var wire 10 * D [9:0] $end
$var wire 10 + F [9:0] $end
$var wire 1 & clk $end
$var reg 10 , L12_D [9:0] $end
$var reg 10 - L12_x1 [9:0] $end
$var reg 10 . L12_x2 [9:0] $end
$var reg 10 / L23_D [9:0] $end
$var reg 10 0 L23_x3 [9:0] $end
$var reg 10 1 L34_D [9:0] $end
$var reg 10 2 L34_F [9:0] $end
$upscope $end
$upscope $end
$scope module stimuli $end
$scope module uut $end
$upscope $end
$upscope $end
$enddefinitions $end
#0
$dumpvars
bx 2
bx 1
bx 0
bx /
bx .
bx -
bx ,
bx +
b11 *
b1000 )
b101 (
b1010 '
0&
b11 %
b1000 $
b101 #
b1010 "
bx !
$end
#5000
b11 ,
1&
#9000
b101 .
b1111 -
#10000
0&
b100 %
b100 *
b1100 $
b1100 )
b111 #
b111 (
b1111 "
b1111 '
#15000
b11 /
b100 ,
1&
#19000
b10100 0
b1000 .
b10110 -
#20000
0&
b110 %
b110 *
b1110 $
b1110 )
b1010 #
b1010 (
b10100 "
b10100 '
#25000
b11 1
b100 /
b110 ,
1&
#29000
b11110 0
b11110 -
#30000
0&
b1000 %
b1000 *
b10010 $
b10010 )
b1100 #
b1100 (
b11001 "
b11001 '
#31000
b111100 !
b111100 +
b111100 2
#35000
b100 1
b110 /
b1000 ,
1&
#39000
b100110 0
b1010 .
b100101 -
