pipelines/pipelineProcessor.v
module PipelineProcessor (
    input clk, reset,
    input [4:0] rs1, rs2, rd,
    input [3:0] func,
    input [31:0] addr,
    output [31:0] mem_out
);

    // Register File
    reg [31:0] register_file [0:31];

    initial begin
        register_file[0] = 32'h00000001;
        register_file[1] = 32'h00000002;
        register_file[2] = 32'h00000003;
        register_file[3] = 32'h00000004;
        register_file[4] = 32'h00000005;
        register_file[5] = 32'h00000006;
        register_file[6] = 32'h00000007;
        register_file[7] = 32'h00000008;
        register_file[8] = 32'h00000009;
        register_file[9] = 32'h0000000A;
        $display("Register file initialized");
    end

    // Pipeline Registers
    reg [31:0] A_EX, B_EX, ALU_OUT_MEM, MEM_OUT;
    reg [4:0] RD_EX, RD_MEM;
    reg [31:0] ADDR_EX, ADDR_MEM;
    reg [3:0] FUNC_EX;

    // Stage 1: Fetch & Decode
    always @(posedge clk) begin
        if (reset) begin
            A_EX <= 0;
            B_EX <= 0;
            RD_EX <= 0;
            FUNC_EX <= 0;
            ADDR_EX <= 0;
        end else begin
            A_EX <= register_file[rs1];
            B_EX <= register_file[rs2];
            RD_EX <= rd;
            FUNC_EX <= func;
            ADDR_EX <= addr;
        end
    end

    // Stage 2: Execute
    reg [31:0] alu_result;
    always @(posedge clk) begin
        if (reset) begin
            ALU_OUT_MEM <= 0;
            RD_MEM <= 0;
            ADDR_MEM <= 0;
        end else begin
            case (FUNC_EX)
                4'b0000: alu_result = A_EX + B_EX;
                4'b0001: alu_result = A_EX - B_EX;
                4'b0010: alu_result = A_EX & B_EX;
                4'b0011: alu_result = A_EX | B_EX;
                default: alu_result = 0;
            endcase
            ALU_OUT_MEM <= alu_result;
            RD_MEM <= RD_EX;
            ADDR_MEM <= ADDR_EX;
        end
    end

    // Stage 3: Write Back (and Memory Output)
    always @(posedge clk) begin
        if (reset) begin
            MEM_OUT <= 0;
        end else begin
            if (RD_MEM != 0)
                register_file[RD_MEM] <= ALU_OUT_MEM;
            MEM_OUT <= ALU_OUT_MEM; // Output to memory (no memory array here)
        end
    end

    assign mem_out = MEM_OUT;

endmodule

pipelines/pipelineProcessor_tb.v
`timescale 1ns / 1ps
`include "pipelineProcessor.v"

module PipelineProcessor_tb;
    reg clk, clk2, reset;
    reg [4:0] rs1, rs2, rd;
    reg [3:0] func;
    reg [31:0] addr;
    wire [31:0] mem_out;

    // Instantiate the Pipeline Processor
    PipelineProcessor uut (
        .clk(clk),
        .reset(reset),
        .rs1(rs1),
        .rs2(rs2),
        .rd(rd),
        .func(func),
        .addr(addr),
        .mem_out(mem_out)
    );

    // initial begin
    //     $dumpfile("waveform.vcd");  
    //     $dumpvars(0, PipelineProcessor_tb);
    //     $dumpvars(1, uut);
    // end

    always #5 clk = ~clk; // Clock toggles every 5ns (Period = 10ns)

    initial begin
        // Initialize signals
        clk = 0; reset = 1;
        rs1 = 0; rs2 = 0; rd = 0; func = 4'b0000; addr = 0;
        #10 reset = 0;

        #10 rs1 = 5; rs2 = 6; rd = 10; func = 4'b0000; addr = 32'h1000;
        
        // #20 rs1 = 3; rs2 = 4; rd = 11; func = 4'b0001; addr = 32'h1004;
        
        // #20 rs1 = 7; rs2 = 8; rd = 12; func = 4'b0010; addr = 32'h1008;
        
        // #20 rs1 = 9; rs2 = 10; rd = 13; func = 4'b0011; addr = 32'h100C;
        
        #50 $stop;
        $finish;
    end

    initial begin
        $monitor("Time = %0t | clk1 = %b | rs1 = %d | rs2 = %d | func = %b | mem_out = %d",
              $time, clk, rs1, rs2, func, mem_out);

    end

endmodule

pipelines/waveform.vcd
$date
	Tue Apr 01 10:59:25 2025
$end
$version
	Icarus Verilog
$end
$timescale
	1ps
$end
$scope module PipelineProcessor_tb $end
$var wire 32 ! mem_out [31:0] $end
$var reg 32 " addr [31:0] $end
$var reg 1 # clk $end
$var reg 4 $ func [3:0] $end
$var reg 5 % rd [4:0] $end
$var reg 1 & reset $end
$var reg 5 ' rs1 [4:0] $end
$var reg 5 ( rs2 [4:0] $end
$scope module uut $end
$var wire 32 ) addr [31:0] $end
$var wire 1 # clk $end
$var wire 4 * func [3:0] $end
$var wire 32 + mem_out [31:0] $end
$var wire 5 , rd [4:0] $end
$var wire 1 & reset $end
$var wire 5 - rs1 [4:0] $end
$var wire 5 . rs2 [4:0] $end
$var reg 32 / ADDR_EX [31:0] $end
$var reg 32 0 ADDR_MEM [31:0] $end
$var reg 32 1 ALU_OUT_MEM [31:0] $end
$var reg 32 2 A_EX [31:0] $end
$var reg 32 3 B_EX [31:0] $end
$var reg 4 4 FUNC_EX [3:0] $end
$var reg 32 5 MEM_OUT [31:0] $end
$var reg 5 6 RD_EX [4:0] $end
$var reg 5 7 RD_MEM [4:0] $end
$var reg 32 8 alu_result [31:0] $end
$upscope $end
$upscope $end
$scope module PipelineProcessor_tb $end
$scope module uut $end
$upscope $end
$upscope $end
$enddefinitions $end
#0
$dumpvars
bx 8
bx 7
bx 6
bx 5
bx 4
bx 3
bx 2
bx 1
bx 0
bx /
b0 .
b0 -
b0 ,
bx +
b0 *
b0 )
b0 (
b0 '
1&
b0 %
b0 $
0#
b0 "
bx !
$end
#5000
b0 /
b0 4
b0 6
b0 3
b0 2
b0 0
b0 7
b0 1
b0 !
b0 +
b0 5
1#
#10000
0#
0&
#15000
b1 3
b1 2
b0 8
1#
#20000
0#
b1000000000000 "
b1000000000000 )
b1010 %
b1010 ,
b110 (
b110 .
b101 '
b101 -
#25000
b1000000000000 /
b1010 6
b111 3
b110 2
b10 1
b10 8
1#
#30000
0#
#35000
b10 !
b10 +
b10 5
b1000000000000 0
b1010 7
b1101 1
b1101 8
1#
#40000
0#
#45000
b1101 !
b1101 +
b1101 5
1#
